challonge_wrapper/__init__.py
challonge_wrapper/challonge_helpers.py
challonge_wrapper/challonge_match.py
challonge_wrapper/challonge_participant.py
challonge_wrapper/challonge_tournament.py
challonge_wrapper/challonge_tourney.py
challonge_wrapper-0.2.1-py3.8.egg-info/PKG-INFO
challonge_wrapper-0.2.1-py3.8.egg-info/SOURCES.txt
challonge_wrapper-0.2.1-py3.8.egg-info/requires.txt
challonge_wrapper-0.2.1-py3.8.egg-info/top_level.txt
challonge_wrapper-0.2.2-py3.8.egg-info/PKG-INFO
challonge_wrapper-0.2.2-py3.8.egg-info/SOURCES.txt
challonge_wrapper-0.2.2-py3.8.egg-info/dependency_links.txt
challonge_wrapper-0.2.2-py3.8.egg-info/requires.txt
challonge_wrapper-0.2.2-py3.8.egg-info/top_level.txt
challonge_wrapper-0.2.0.dist-info/LICENSE
challonge_wrapper-0.2.0.dist-info/METADATA
challonge_wrapper-0.2.0.dist-info/top_level.txt
challonge_wrapper-0.2.1.dist-info/LICENSE
challonge_wrapper-0.2.1.dist-info/METADATA
challonge_wrapper-0.2.1.dist-info/top_level.txt
challonge_wrapper-0.2.2.dist-info/LICENSE
challonge_wrapper-0.2.2.dist-info/METADATA
challonge_wrapper-0.2.2.dist-info/top_level.txt
challonge_wrapper-0.2.3.dist-info/LICENSE
challonge_wrapper-0.2.3.dist-info/METADATA
challonge_wrapper-0.2.3.dist-info/WHEEL
challonge_wrapper-0.2.3.dist-info/top_level.txt
challonge_wrapper-0.2.3.dist-info/RECORD
