Metadata-Version: 2.1
Name: challonge-wrapper
Version: 0.2.3
Summary: Challonge REST API wrappers
Home-page: https://github.com/Impasse52/challonge-python-wrapper
Author: Giuseppe Termerissa
Author-email: linkohprismriver@gmail.com
License: MIT
Platform: UNKNOWN
Requires-Dist: requests
